<?xml version="1.0" encoding="UTF-8"?>
<ROOT xmlns="http://www.cdn.com.pl/optima/dokument"><DOKUMENT><NAGLOWEK><GENERATOR>Comarch Opt!ma</GENERATOR><TYP_DOKUMENTU>302</TYP_DOKUMENTU><RODZAJ_DOKUMENTU>302004</RODZAJ_DOKUMENTU><FV_MARZA>0</FV_MARZA><FV_MARZA_RODZAJ>0</FV_MARZA_RODZAJ><NUMER_PELNY>FA/645/2023</NUMER_PELNY><DATA_DOKUMENTU>2023-02-01</DATA_DOKUMENTU><DATA_WYSTAWIENIA>2023-02-01</DATA_WYSTAWIENIA><DATA_OPERACJI>2023-02-01</DATA_OPERACJI><TERMIN_ZWROTU_KAUCJI>2023-04-02</TERMIN_ZWROTU_KAUCJI><KOREKTA>0</KOREKTA><DETAL>0</DETAL><TYP_NETTO_BRUTTO>2</TYP_NETTO_BRUTTO><RABAT>0.00</RABAT><OPIS>Dok.: FA/645/2023 (Faktura sprzedaży z wygenerowanym WZ)</OPIS><PLATNIK><KOD>PAULA</KOD><NIP_KRAJ>PL</NIP_KRAJ><NIP>9662016861</NIP><GLN/><NAZWA>SD Paula Senderacka</NAZWA><MPP>0</MPP><ADRES><KOD_POCZTOWY>18-106</KOD_POCZTOWY><MIASTO>Tołcze</MIASTO><ULICA> 29</ULICA><KRAJ>Polska</KRAJ></ADRES></PLATNIK><ODBIORCA><KOD>PAULA</KOD><NIP_KRAJ>PL</NIP_KRAJ><NIP>9662016861</NIP><GLN/><NAZWA>SD Paula Senderacka</NAZWA><ADRES><KOD_POCZTOWY>18-106</KOD_POCZTOWY><MIASTO>Tołcze</MIASTO><ULICA> 29</ULICA><KRAJ>Polska</KRAJ></ADRES></ODBIORCA><SPRZEDAWCA><NIP_KRAJ>PL</NIP_KRAJ><NIP>546-000-03-17</NIP><GLN>0000000000000</GLN><NAZWA>P.H.U. "KROKUS" HURTOWNIA KWIATÓW LESZEK WOŁKOWICZ</NAZWA><ADRES><KOD_POCZTOWY>15-257</KOD_POCZTOWY><MIASTO>BIAŁYSTOK</MIASTO><ULICA>ul. A. MICKIEWICZA 95</ULICA><KRAJ>Polska</KRAJ></ADRES><NUMER_KONTA_BANKOWEGO>22-12405211-1111000049289196</NUMER_KONTA_BANKOWEGO><NAZWA_BANKU>BANK PEKAO SA</NAZWA_BANKU></SPRZEDAWCA><KATEGORIA><KOD/><OPIS/></KATEGORIA><PLATNOSC><FORMA>Karta</FORMA><TERMIN>2023-02-01</TERMIN><MPP>0</MPP></PLATNOSC><WALUTA><SYMBOL>PLN</SYMBOL><KURS_L>1.00</KURS_L><KURS_M>1</KURS_M><PLAT_WAL_OD_PLN>0</PLAT_WAL_OD_PLN><KURS_NUMER>3</KURS_NUMER><KURS_DATA>2023-02-01</KURS_DATA></WALUTA><KWOTY><RAZEM_NETTO_WAL>529.23</RAZEM_NETTO_WAL><RAZEM_NETTO>529.23</RAZEM_NETTO><RAZEM_BRUTTO>650.95</RAZEM_BRUTTO><RAZEM_VAT>121.72</RAZEM_VAT></KWOTY><MAGAZYN_ZRODLOWY>MAGAZYN</MAGAZYN_ZRODLOWY><MAGAZYN_DOCELOWY/><KAUCJE_PLATNOSCI>0</KAUCJE_PLATNOSCI><BLOKADA_PLATNOSCI>0</BLOKADA_PLATNOSCI><VAT_DLA_DOK_WAL>0</VAT_DLA_DOK_WAL><TRYB_NETTO_VAT>0</TRYB_NETTO_VAT><STATUS_PLATNIKA>0</STATUS_PLATNIKA><ROZLICZAM_PODATEK_W_OSS>0</ROZLICZAM_PODATEK_W_OSS></NAGLOWEK><POZYCJE><POZYCJA><LP>1</LP><TOWAR><KOD>710160</KOD><NAZWA>FLIZELINA MIX KOLORÓW</NAZWA><OPIS/><EAN>710160</EAN><SWW/><NUMER_KATALOGOWY/><MPP>0</MPP></TOWAR><STAWKA_VAT><STAWKA>23.00</STAWKA><FLAGA>2</FLAGA><ZRODLOWA>0.00</ZRODLOWA></STAWKA_VAT><CENY><CENAZCZTEREMAMIEJSCAMI>0</CENAZCZTEREMAMIEJSCAMI><POCZATKOWA_WAL_CENNIKA>8.4000</POCZATKOWA_WAL_CENNIKA><POCZATKOWA_WAL_DOKUMENTU>8.4000</POCZATKOWA_WAL_DOKUMENTU><PO_RABACIE_WAL_CENNIKA>8.4000</PO_RABACIE_WAL_CENNIKA><PO_RABACIE_PLN>8.4000</PO_RABACIE_PLN><PO_RABACIE_WAL_DOKUMENTU>8.4000</PO_RABACIE_WAL_DOKUMENTU></CENY><WALUTA><SYMBOL>PLN</SYMBOL><KURS_L>1.00</KURS_L><KURS_M>1</KURS_M></WALUTA><RABAT>0.00</RABAT><WARTOSC_NETTO>6.83</WARTOSC_NETTO><WARTOSC_BRUTTO>8.40</WARTOSC_BRUTTO><WARTOSC_NETTO_WAL>6.83</WARTOSC_NETTO_WAL><WARTOSC_BRUTTO_WAL>8.40</WARTOSC_BRUTTO_WAL><ILOSC>1.0000</ILOSC><JM>szt</JM><JM_CALKOWITE>0.00</JM_CALKOWITE><JM_ZLOZONA><JMZ>szt</JMZ><JM_PRZELICZNIK_L>1.00</JM_PRZELICZNIK_L><JM_PRZELICZNIK_M>1</JM_PRZELICZNIK_M></JM_ZLOZONA></POZYCJA><POZYCJA><LP>2</LP><TOWAR><KOD>717522</KOD><NAZWA>SUSZ REPENS 25-35 CM 100SZT/OP</NAZWA><OPIS/><EAN>5907692251336</EAN><SWW/><NUMER_KATALOGOWY/><MPP>0</MPP></TOWAR><STAWKA_VAT><STAWKA>23.00</STAWKA><FLAGA>2</FLAGA><ZRODLOWA>0.00</ZRODLOWA></STAWKA_VAT><CENY><CENAZCZTEREMAMIEJSCAMI>0</CENAZCZTEREMAMIEJSCAMI><POCZATKOWA_WAL_CENNIKA>3.8000</POCZATKOWA_WAL_CENNIKA><POCZATKOWA_WAL_DOKUMENTU>3.8000</POCZATKOWA_WAL_DOKUMENTU><PO_RABACIE_WAL_CENNIKA>3.8000</PO_RABACIE_WAL_CENNIKA><PO_RABACIE_PLN>3.8000</PO_RABACIE_PLN><PO_RABACIE_WAL_DOKUMENTU>3.8000</PO_RABACIE_WAL_DOKUMENTU></CENY><WALUTA><SYMBOL>PLN</SYMBOL><KURS_L>1.00</KURS_L><KURS_M>1</KURS_M></WALUTA><RABAT>0.00</RABAT><WARTOSC_NETTO>61.79</WARTOSC_NETTO><WARTOSC_BRUTTO>76.00</WARTOSC_BRUTTO><WARTOSC_NETTO_WAL>61.79</WARTOSC_NETTO_WAL><WARTOSC_BRUTTO_WAL>76.00</WARTOSC_BRUTTO_WAL><ILOSC>20.0000</ILOSC><JM>szt</JM><JM_CALKOWITE>0.00</JM_CALKOWITE><JM_ZLOZONA><JMZ>szt</JMZ><JM_PRZELICZNIK_L>1.00</JM_PRZELICZNIK_L><JM_PRZELICZNIK_M>1</JM_PRZELICZNIK_M></JM_ZLOZONA></POZYCJA><POZYCJA><LP>3</LP><TOWAR><KOD>717454</KOD><NAZWA>WSTĄŻKA RYPS 25MMx25Y</NAZWA><OPIS/><EAN>5902581035066</EAN><SWW/><NUMER_KATALOGOWY/><MPP>0</MPP></TOWAR><STAWKA_VAT><STAWKA>23.00</STAWKA><FLAGA>2</FLAGA><ZRODLOWA>0.00</ZRODLOWA></STAWKA_VAT><CENY><CENAZCZTEREMAMIEJSCAMI>0</CENAZCZTEREMAMIEJSCAMI><POCZATKOWA_WAL_CENNIKA>7.7000</POCZATKOWA_WAL_CENNIKA><POCZATKOWA_WAL_DOKUMENTU>7.7000</POCZATKOWA_WAL_DOKUMENTU><PO_RABACIE_WAL_CENNIKA>7.7000</PO_RABACIE_WAL_CENNIKA><PO_RABACIE_PLN>7.7000</PO_RABACIE_PLN><PO_RABACIE_WAL_DOKUMENTU>7.7000</PO_RABACIE_WAL_DOKUMENTU></CENY><WALUTA><SYMBOL>PLN</SYMBOL><KURS_L>1.00</KURS_L><KURS_M>1</KURS_M></WALUTA><RABAT>0.00</RABAT><WARTOSC_NETTO>6.26</WARTOSC_NETTO><WARTOSC_BRUTTO>7.70</WARTOSC_BRUTTO><WARTOSC_NETTO_WAL>6.26</WARTOSC_NETTO_WAL><WARTOSC_BRUTTO_WAL>7.70</WARTOSC_BRUTTO_WAL><ILOSC>1.0000</ILOSC><JM>szt</JM><JM_CALKOWITE>0.00</JM_CALKOWITE><JM_ZLOZONA><JMZ>szt</JMZ><JM_PRZELICZNIK_L>1.00</JM_PRZELICZNIK_L><JM_PRZELICZNIK_M>1</JM_PRZELICZNIK_M></JM_ZLOZONA></POZYCJA><POZYCJA><LP>4</LP><TOWAR><KOD>712823</KOD><NAZWA>WSTĄŻKA GROSGRAIN RIBBON BLACK 2,5CMX22M</NAZWA><OPIS/><EAN>5901720246592</EAN><SWW/><NUMER_KATALOGOWY/><MPP>0</MPP></TOWAR><STAWKA_VAT><STAWKA>23.00</STAWKA><FLAGA>2</FLAGA><ZRODLOWA>0.00</ZRODLOWA></STAWKA_VAT><CENY><CENAZCZTEREMAMIEJSCAMI>0</CENAZCZTEREMAMIEJSCAMI><POCZATKOWA_WAL_CENNIKA>7.7000</POCZATKOWA_WAL_CENNIKA><POCZATKOWA_WAL_DOKUMENTU>7.7000</POCZATKOWA_WAL_DOKUMENTU><PO_RABACIE_WAL_CENNIKA>7.7000</PO_RABACIE_WAL_CENNIKA><PO_RABACIE_PLN>7.7000</PO_RABACIE_PLN><PO_RABACIE_WAL_DOKUMENTU>7.7000</PO_RABACIE_WAL_DOKUMENTU></CENY><WALUTA><SYMBOL>PLN</SYMBOL><KURS_L>1.00</KURS_L><KURS_M>1</KURS_M></WALUTA><RABAT>0.00</RABAT><WARTOSC_NETTO>6.26</WARTOSC_NETTO><WARTOSC_BRUTTO>7.70</WARTOSC_BRUTTO><WARTOSC_NETTO_WAL>6.26</WARTOSC_NETTO_WAL><WARTOSC_BRUTTO_WAL>7.70</WARTOSC_BRUTTO_WAL><ILOSC>1.0000</ILOSC><JM>szt.</JM><JM_CALKOWITE>0.00</JM_CALKOWITE><JM_ZLOZONA><JMZ>szt.</JMZ><JM_PRZELICZNIK_L>1.00</JM_PRZELICZNIK_L><JM_PRZELICZNIK_M>1</JM_PRZELICZNIK_M></JM_ZLOZONA></POZYCJA><POZYCJA><LP>5</LP><TOWAR><KOD>716369</KOD><NAZWA>WSTĄŻKA RYPS 25MM X 25Y</NAZWA><OPIS/><EAN>5902581026958</EAN><SWW/><NUMER_KATALOGOWY/><MPP>0</MPP></TOWAR><STAWKA_VAT><STAWKA>23.00</STAWKA><FLAGA>2</FLAGA><ZRODLOWA>0.00</ZRODLOWA></STAWKA_VAT><CENY><CENAZCZTEREMAMIEJSCAMI>0</CENAZCZTEREMAMIEJSCAMI><POCZATKOWA_WAL_CENNIKA>7.7000</POCZATKOWA_WAL_CENNIKA><POCZATKOWA_WAL_DOKUMENTU>7.7000</POCZATKOWA_WAL_DOKUMENTU><PO_RABACIE_WAL_CENNIKA>7.7000</PO_RABACIE_WAL_CENNIKA><PO_RABACIE_PLN>7.7000</PO_RABACIE_PLN><PO_RABACIE_WAL_DOKUMENTU>7.7000</PO_RABACIE_WAL_DOKUMENTU></CENY><WALUTA><SYMBOL>PLN</SYMBOL><KURS_L>1.00</KURS_L><KURS_M>1</KURS_M></WALUTA><RABAT>0.00</RABAT><WARTOSC_NETTO>6.26</WARTOSC_NETTO><WARTOSC_BRUTTO>7.70</WARTOSC_BRUTTO><WARTOSC_NETTO_WAL>6.26</WARTOSC_NETTO_WAL><WARTOSC_BRUTTO_WAL>7.70</WARTOSC_BRUTTO_WAL><ILOSC>1.0000</ILOSC><JM>szt</JM><JM_CALKOWITE>0.00</JM_CALKOWITE><JM_ZLOZONA><JMZ>szt</JMZ><JM_PRZELICZNIK_L>1.00</JM_PRZELICZNIK_L><JM_PRZELICZNIK_M>1</JM_PRZELICZNIK_M></JM_ZLOZONA></POZYCJA><POZYCJA><LP>6</LP><TOWAR><KOD>666337</KOD><NAZWA>KPL.PUDEŁEK OZDOBNYCH W2048</NAZWA><OPIS/><EAN>5903288080588</EAN><SWW/><NUMER_KATALOGOWY/><MPP>0</MPP></TOWAR><STAWKA_VAT><STAWKA>23.00</STAWKA><FLAGA>2</FLAGA><ZRODLOWA>0.00</ZRODLOWA></STAWKA_VAT><CENY><CENAZCZTEREMAMIEJSCAMI>0</CENAZCZTEREMAMIEJSCAMI><POCZATKOWA_WAL_CENNIKA>78.3000</POCZATKOWA_WAL_CENNIKA><POCZATKOWA_WAL_DOKUMENTU>78.3000</POCZATKOWA_WAL_DOKUMENTU><PO_RABACIE_WAL_CENNIKA>78.3000</PO_RABACIE_WAL_CENNIKA><PO_RABACIE_PLN>78.3000</PO_RABACIE_PLN><PO_RABACIE_WAL_DOKUMENTU>78.3000</PO_RABACIE_WAL_DOKUMENTU></CENY><WALUTA><SYMBOL>PLN</SYMBOL><KURS_L>1.00</KURS_L><KURS_M>1</KURS_M></WALUTA><RABAT>0.00</RABAT><WARTOSC_NETTO>63.66</WARTOSC_NETTO><WARTOSC_BRUTTO>78.30</WARTOSC_BRUTTO><WARTOSC_NETTO_WAL>63.66</WARTOSC_NETTO_WAL><WARTOSC_BRUTTO_WAL>78.30</WARTOSC_BRUTTO_WAL><ILOSC>1.0000</ILOSC><JM>KPL</JM><JM_CALKOWITE>0.00</JM_CALKOWITE><JM_ZLOZONA><JMZ>KPL</JMZ><JM_PRZELICZNIK_L>1.00</JM_PRZELICZNIK_L><JM_PRZELICZNIK_M>1</JM_PRZELICZNIK_M></JM_ZLOZONA></POZYCJA><POZYCJA><LP>7</LP><TOWAR><KOD>716259</KOD><NAZWA>PIÓRKA TOREBKA</NAZWA><OPIS/><EAN/><SWW/><NUMER_KATALOGOWY/><MPP>0</MPP></TOWAR><STAWKA_VAT><STAWKA>23.00</STAWKA><FLAGA>2</FLAGA><ZRODLOWA>0.00</ZRODLOWA></STAWKA_VAT><CENY><CENAZCZTEREMAMIEJSCAMI>0</CENAZCZTEREMAMIEJSCAMI><POCZATKOWA_WAL_CENNIKA>2.8000</POCZATKOWA_WAL_CENNIKA><POCZATKOWA_WAL_DOKUMENTU>2.8000</POCZATKOWA_WAL_DOKUMENTU><PO_RABACIE_WAL_CENNIKA>2.8000</PO_RABACIE_WAL_CENNIKA><PO_RABACIE_PLN>2.8000</PO_RABACIE_PLN><PO_RABACIE_WAL_DOKUMENTU>2.8000</PO_RABACIE_WAL_DOKUMENTU></CENY><WALUTA><SYMBOL>PLN</SYMBOL><KURS_L>1.00</KURS_L><KURS_M>1</KURS_M></WALUTA><RABAT>0.00</RABAT><WARTOSC_NETTO>13.66</WARTOSC_NETTO><WARTOSC_BRUTTO>16.80</WARTOSC_BRUTTO><WARTOSC_NETTO_WAL>13.66</WARTOSC_NETTO_WAL><WARTOSC_BRUTTO_WAL>16.80</WARTOSC_BRUTTO_WAL><ILOSC>6.0000</ILOSC><JM>szt</JM><JM_CALKOWITE>0.00</JM_CALKOWITE><JM_ZLOZONA><JMZ>szt</JMZ><JM_PRZELICZNIK_L>1.00</JM_PRZELICZNIK_L><JM_PRZELICZNIK_M>1</JM_PRZELICZNIK_M></JM_ZLOZONA></POZYCJA><POZYCJA><LP>8</LP><TOWAR><KOD>501525</KOD><NAZWA>DRUT STALOWY ZIELONY NA SZPULCE - 100g (0,35mm x 70m)</NAZWA><OPIS/><EAN>501525</EAN><SWW/><NUMER_KATALOGOWY/><MPP>0</MPP></TOWAR><STAWKA_VAT><STAWKA>23.00</STAWKA><FLAGA>2</FLAGA><ZRODLOWA>0.00</ZRODLOWA></STAWKA_VAT><CENY><CENAZCZTEREMAMIEJSCAMI>0</CENAZCZTEREMAMIEJSCAMI><POCZATKOWA_WAL_CENNIKA>4.0000</POCZATKOWA_WAL_CENNIKA><POCZATKOWA_WAL_DOKUMENTU>4.0000</POCZATKOWA_WAL_DOKUMENTU><PO_RABACIE_WAL_CENNIKA>4.0000</PO_RABACIE_WAL_CENNIKA><PO_RABACIE_PLN>4.0000</PO_RABACIE_PLN><PO_RABACIE_WAL_DOKUMENTU>4.0000</PO_RABACIE_WAL_DOKUMENTU></CENY><WALUTA><SYMBOL>PLN</SYMBOL><KURS_L>1.00</KURS_L><KURS_M>1</KURS_M></WALUTA><RABAT>0.00</RABAT><WARTOSC_NETTO>3.25</WARTOSC_NETTO><WARTOSC_BRUTTO>4.00</WARTOSC_BRUTTO><WARTOSC_NETTO_WAL>3.25</WARTOSC_NETTO_WAL><WARTOSC_BRUTTO_WAL>4.00</WARTOSC_BRUTTO_WAL><ILOSC>1.0000</ILOSC><JM>szt.</JM><JM_CALKOWITE>0.00</JM_CALKOWITE><JM_ZLOZONA><JMZ>szt.</JMZ><JM_PRZELICZNIK_L>1.00</JM_PRZELICZNIK_L><JM_PRZELICZNIK_M>1</JM_PRZELICZNIK_M></JM_ZLOZONA></POZYCJA><POZYCJA><LP>9</LP><TOWAR><KOD>717500</KOD><NAZWA>DRUCIK OZDOBNY RZ18M09-33</NAZWA><OPIS/><EAN>5902918770394</EAN><SWW/><NUMER_KATALOGOWY/><MPP>0</MPP></TOWAR><STAWKA_VAT><STAWKA>23.00</STAWKA><FLAGA>2</FLAGA><ZRODLOWA>0.00</ZRODLOWA></STAWKA_VAT><CENY><CENAZCZTEREMAMIEJSCAMI>0</CENAZCZTEREMAMIEJSCAMI><POCZATKOWA_WAL_CENNIKA>3.7500</POCZATKOWA_WAL_CENNIKA><POCZATKOWA_WAL_DOKUMENTU>3.7500</POCZATKOWA_WAL_DOKUMENTU><PO_RABACIE_WAL_CENNIKA>3.7500</PO_RABACIE_WAL_CENNIKA><PO_RABACIE_PLN>3.7500</PO_RABACIE_PLN><PO_RABACIE_WAL_DOKUMENTU>3.7500</PO_RABACIE_WAL_DOKUMENTU></CENY><WALUTA><SYMBOL>PLN</SYMBOL><KURS_L>1.00</KURS_L><KURS_M>1</KURS_M></WALUTA><RABAT>0.00</RABAT><WARTOSC_NETTO>3.05</WARTOSC_NETTO><WARTOSC_BRUTTO>3.75</WARTOSC_BRUTTO><WARTOSC_NETTO_WAL>3.05</WARTOSC_NETTO_WAL><WARTOSC_BRUTTO_WAL>3.75</WARTOSC_BRUTTO_WAL><ILOSC>1.0000</ILOSC><JM>szt.</JM><JM_CALKOWITE>0.00</JM_CALKOWITE><JM_ZLOZONA><JMZ>szt.</JMZ><JM_PRZELICZNIK_L>1.00</JM_PRZELICZNIK_L><JM_PRZELICZNIK_M>1</JM_PRZELICZNIK_M></JM_ZLOZONA></POZYCJA><POZYCJA><LP>10</LP><TOWAR><KOD>251876</KOD><NAZWA>KWIAT SZTUCZNY FS71</NAZWA><OPIS/><EAN>5901292414115</EAN><SWW/><NUMER_KATALOGOWY/><MPP>0</MPP></TOWAR><STAWKA_VAT><STAWKA>23.00</STAWKA><FLAGA>2</FLAGA><ZRODLOWA>0.00</ZRODLOWA></STAWKA_VAT><CENY><CENAZCZTEREMAMIEJSCAMI>0</CENAZCZTEREMAMIEJSCAMI><POCZATKOWA_WAL_CENNIKA>2.5000</POCZATKOWA_WAL_CENNIKA><POCZATKOWA_WAL_DOKUMENTU>2.5000</POCZATKOWA_WAL_DOKUMENTU><PO_RABACIE_WAL_CENNIKA>2.5000</PO_RABACIE_WAL_CENNIKA><PO_RABACIE_PLN>2.5000</PO_RABACIE_PLN><PO_RABACIE_WAL_DOKUMENTU>2.5000</PO_RABACIE_WAL_DOKUMENTU></CENY><WALUTA><SYMBOL>PLN</SYMBOL><KURS_L>1.00</KURS_L><KURS_M>1</KURS_M></WALUTA><RABAT>0.00</RABAT><WARTOSC_NETTO>48.78</WARTOSC_NETTO><WARTOSC_BRUTTO>60.00</WARTOSC_BRUTTO><WARTOSC_NETTO_WAL>48.78</WARTOSC_NETTO_WAL><WARTOSC_BRUTTO_WAL>60.00</WARTOSC_BRUTTO_WAL><ILOSC>24.0000</ILOSC><JM>szt</JM><JM_CALKOWITE>0.00</JM_CALKOWITE><JM_ZLOZONA><JMZ>szt</JMZ><JM_PRZELICZNIK_L>1.00</JM_PRZELICZNIK_L><JM_PRZELICZNIK_M>1</JM_PRZELICZNIK_M></JM_ZLOZONA></POZYCJA><POZYCJA><LP>11</LP><TOWAR><KOD>250896</KOD><NAZWA>GIRLANDA LIŚĆ CV11246</NAZWA><OPIS/><EAN>5900290989007</EAN><SWW/><NUMER_KATALOGOWY/><MPP>0</MPP></TOWAR><STAWKA_VAT><STAWKA>23.00</STAWKA><FLAGA>2</FLAGA><ZRODLOWA>0.00</ZRODLOWA></STAWKA_VAT><CENY><CENAZCZTEREMAMIEJSCAMI>0</CENAZCZTEREMAMIEJSCAMI><POCZATKOWA_WAL_CENNIKA>38.5000</POCZATKOWA_WAL_CENNIKA><POCZATKOWA_WAL_DOKUMENTU>38.5000</POCZATKOWA_WAL_DOKUMENTU><PO_RABACIE_WAL_CENNIKA>38.5000</PO_RABACIE_WAL_CENNIKA><PO_RABACIE_PLN>38.5000</PO_RABACIE_PLN><PO_RABACIE_WAL_DOKUMENTU>38.5000</PO_RABACIE_WAL_DOKUMENTU></CENY><WALUTA><SYMBOL>PLN</SYMBOL><KURS_L>1.00</KURS_L><KURS_M>1</KURS_M></WALUTA><RABAT>0.00</RABAT><WARTOSC_NETTO>125.20</WARTOSC_NETTO><WARTOSC_BRUTTO>154.00</WARTOSC_BRUTTO><WARTOSC_NETTO_WAL>125.20</WARTOSC_NETTO_WAL><WARTOSC_BRUTTO_WAL>154.00</WARTOSC_BRUTTO_WAL><ILOSC>4.0000</ILOSC><JM>szt.</JM><JM_CALKOWITE>0.00</JM_CALKOWITE><JM_ZLOZONA><JMZ>szt.</JMZ><JM_PRZELICZNIK_L>1.00</JM_PRZELICZNIK_L><JM_PRZELICZNIK_M>1</JM_PRZELICZNIK_M></JM_ZLOZONA></POZYCJA><POZYCJA><LP>12</LP><TOWAR><KOD>251567</KOD><NAZWA>KWIATY SZTUCZNE GAŁĄZKA OZDOBNA CV17776-1</NAZWA><OPIS/><EAN>5900291338446</EAN><SWW/><NUMER_KATALOGOWY/><MPP>0</MPP></TOWAR><STAWKA_VAT><STAWKA>23.00</STAWKA><FLAGA>2</FLAGA><ZRODLOWA>0.00</ZRODLOWA></STAWKA_VAT><CENY><CENAZCZTEREMAMIEJSCAMI>0</CENAZCZTEREMAMIEJSCAMI><POCZATKOWA_WAL_CENNIKA>19.6000</POCZATKOWA_WAL_CENNIKA><POCZATKOWA_WAL_DOKUMENTU>19.6000</POCZATKOWA_WAL_DOKUMENTU><PO_RABACIE_WAL_CENNIKA>19.6000</PO_RABACIE_WAL_CENNIKA><PO_RABACIE_PLN>19.6000</PO_RABACIE_PLN><PO_RABACIE_WAL_DOKUMENTU>19.6000</PO_RABACIE_WAL_DOKUMENTU></CENY><WALUTA><SYMBOL>PLN</SYMBOL><KURS_L>1.00</KURS_L><KURS_M>1</KURS_M></WALUTA><RABAT>0.00</RABAT><WARTOSC_NETTO>111.54</WARTOSC_NETTO><WARTOSC_BRUTTO>137.20</WARTOSC_BRUTTO><WARTOSC_NETTO_WAL>111.54</WARTOSC_NETTO_WAL><WARTOSC_BRUTTO_WAL>137.20</WARTOSC_BRUTTO_WAL><ILOSC>7.0000</ILOSC><JM>szt</JM><JM_CALKOWITE>0.00</JM_CALKOWITE><JM_ZLOZONA><JMZ>szt</JMZ><JM_PRZELICZNIK_L>1.00</JM_PRZELICZNIK_L><JM_PRZELICZNIK_M>1</JM_PRZELICZNIK_M></JM_ZLOZONA></POZYCJA><POZYCJA><LP>13</LP><TOWAR><KOD>252266</KOD><NAZWA>KWIAT SZTUCZNY KX74251</NAZWA><OPIS/><EAN/><SWW/><NUMER_KATALOGOWY/><MPP>0</MPP></TOWAR><STAWKA_VAT><STAWKA>23.00</STAWKA><FLAGA>2</FLAGA><ZRODLOWA>0.00</ZRODLOWA></STAWKA_VAT><CENY><CENAZCZTEREMAMIEJSCAMI>0</CENAZCZTEREMAMIEJSCAMI><POCZATKOWA_WAL_CENNIKA>0.8500</POCZATKOWA_WAL_CENNIKA><POCZATKOWA_WAL_DOKUMENTU>0.8500</POCZATKOWA_WAL_DOKUMENTU><PO_RABACIE_WAL_CENNIKA>0.8500</PO_RABACIE_WAL_CENNIKA><PO_RABACIE_PLN>0.8500</PO_RABACIE_PLN><PO_RABACIE_WAL_DOKUMENTU>0.8500</PO_RABACIE_WAL_DOKUMENTU></CENY><WALUTA><SYMBOL>PLN</SYMBOL><KURS_L>1.00</KURS_L><KURS_M>1</KURS_M></WALUTA><RABAT>0.00</RABAT><WARTOSC_NETTO>16.59</WARTOSC_NETTO><WARTOSC_BRUTTO>20.40</WARTOSC_BRUTTO><WARTOSC_NETTO_WAL>16.59</WARTOSC_NETTO_WAL><WARTOSC_BRUTTO_WAL>20.40</WARTOSC_BRUTTO_WAL><ILOSC>24.0000</ILOSC><JM>szt.</JM><JM_CALKOWITE>0.00</JM_CALKOWITE><JM_ZLOZONA><JMZ>szt.</JMZ><JM_PRZELICZNIK_L>1.00</JM_PRZELICZNIK_L><JM_PRZELICZNIK_M>1</JM_PRZELICZNIK_M></JM_ZLOZONA></POZYCJA><POZYCJA><LP>14</LP><TOWAR><KOD>251257</KOD><NAZWA>KWIATY SZTUCZNE LIŚĆ K7-1/9</NAZWA><OPIS/><EAN/><SWW/><NUMER_KATALOGOWY/><MPP>0</MPP></TOWAR><STAWKA_VAT><STAWKA>23.00</STAWKA><FLAGA>2</FLAGA><ZRODLOWA>0.00</ZRODLOWA></STAWKA_VAT><CENY><CENAZCZTEREMAMIEJSCAMI>0</CENAZCZTEREMAMIEJSCAMI><POCZATKOWA_WAL_CENNIKA>1.0000</POCZATKOWA_WAL_CENNIKA><POCZATKOWA_WAL_DOKUMENTU>1.0000</POCZATKOWA_WAL_DOKUMENTU><PO_RABACIE_WAL_CENNIKA>1.0000</PO_RABACIE_WAL_CENNIKA><PO_RABACIE_PLN>1.0000</PO_RABACIE_PLN><PO_RABACIE_WAL_DOKUMENTU>1.0000</PO_RABACIE_WAL_DOKUMENTU></CENY><WALUTA><SYMBOL>PLN</SYMBOL><KURS_L>1.00</KURS_L><KURS_M>1</KURS_M></WALUTA><RABAT>0.00</RABAT><WARTOSC_NETTO>19.51</WARTOSC_NETTO><WARTOSC_BRUTTO>24.00</WARTOSC_BRUTTO><WARTOSC_NETTO_WAL>19.51</WARTOSC_NETTO_WAL><WARTOSC_BRUTTO_WAL>24.00</WARTOSC_BRUTTO_WAL><ILOSC>24.0000</ILOSC><JM>szt</JM><JM_CALKOWITE>0.00</JM_CALKOWITE><JM_ZLOZONA><JMZ>szt</JMZ><JM_PRZELICZNIK_L>1.00</JM_PRZELICZNIK_L><JM_PRZELICZNIK_M>1</JM_PRZELICZNIK_M></JM_ZLOZONA></POZYCJA><POZYCJA><LP>15</LP><TOWAR><KOD>250268</KOD><NAZWA>HORTENSJA W./LE18</NAZWA><OPIS/><EAN>5901292493493</EAN><SWW/><NUMER_KATALOGOWY/><MPP>0</MPP></TOWAR><STAWKA_VAT><STAWKA>23.00</STAWKA><FLAGA>2</FLAGA><ZRODLOWA>0.00</ZRODLOWA></STAWKA_VAT><CENY><CENAZCZTEREMAMIEJSCAMI>0</CENAZCZTEREMAMIEJSCAMI><POCZATKOWA_WAL_CENNIKA>2.3500</POCZATKOWA_WAL_CENNIKA><POCZATKOWA_WAL_DOKUMENTU>2.3500</POCZATKOWA_WAL_DOKUMENTU><PO_RABACIE_WAL_CENNIKA>2.3500</PO_RABACIE_WAL_CENNIKA><PO_RABACIE_PLN>2.3500</PO_RABACIE_PLN><PO_RABACIE_WAL_DOKUMENTU>2.3500</PO_RABACIE_WAL_DOKUMENTU></CENY><WALUTA><SYMBOL>PLN</SYMBOL><KURS_L>1.00</KURS_L><KURS_M>1</KURS_M></WALUTA><RABAT>0.00</RABAT><WARTOSC_NETTO>3.82</WARTOSC_NETTO><WARTOSC_BRUTTO>4.70</WARTOSC_BRUTTO><WARTOSC_NETTO_WAL>3.82</WARTOSC_NETTO_WAL><WARTOSC_BRUTTO_WAL>4.70</WARTOSC_BRUTTO_WAL><ILOSC>2.0000</ILOSC><JM>szt</JM><JM_CALKOWITE>0.00</JM_CALKOWITE><JM_ZLOZONA><JMZ>szt</JMZ><JM_PRZELICZNIK_L>1.00</JM_PRZELICZNIK_L><JM_PRZELICZNIK_M>1</JM_PRZELICZNIK_M></JM_ZLOZONA></POZYCJA><POZYCJA><LP>16</LP><TOWAR><KOD>251269</KOD><NAZWA>KWIATY SZTUCZNE J248</NAZWA><OPIS/><EAN/><SWW/><NUMER_KATALOGOWY/><MPP>0</MPP></TOWAR><STAWKA_VAT><STAWKA>23.00</STAWKA><FLAGA>2</FLAGA><ZRODLOWA>0.00</ZRODLOWA></STAWKA_VAT><CENY><CENAZCZTEREMAMIEJSCAMI>0</CENAZCZTEREMAMIEJSCAMI><POCZATKOWA_WAL_CENNIKA>3.5000</POCZATKOWA_WAL_CENNIKA><POCZATKOWA_WAL_DOKUMENTU>3.5000</POCZATKOWA_WAL_DOKUMENTU><PO_RABACIE_WAL_CENNIKA>3.5000</PO_RABACIE_WAL_CENNIKA><PO_RABACIE_PLN>3.5000</PO_RABACIE_PLN><PO_RABACIE_WAL_DOKUMENTU>3.5000</PO_RABACIE_WAL_DOKUMENTU></CENY><WALUTA><SYMBOL>PLN</SYMBOL><KURS_L>1.00</KURS_L><KURS_M>1</KURS_M></WALUTA><RABAT>0.00</RABAT><WARTOSC_NETTO>8.54</WARTOSC_NETTO><WARTOSC_BRUTTO>10.50</WARTOSC_BRUTTO><WARTOSC_NETTO_WAL>8.54</WARTOSC_NETTO_WAL><WARTOSC_BRUTTO_WAL>10.50</WARTOSC_BRUTTO_WAL><ILOSC>3.0000</ILOSC><JM>szt</JM><JM_CALKOWITE>0.00</JM_CALKOWITE><JM_ZLOZONA><JMZ>szt</JMZ><JM_PRZELICZNIK_L>1.00</JM_PRZELICZNIK_L><JM_PRZELICZNIK_M>1</JM_PRZELICZNIK_M></JM_ZLOZONA></POZYCJA><POZYCJA><LP>17</LP><TOWAR><KOD>251767</KOD><NAZWA>KWIAT SZTUCZNY A985</NAZWA><OPIS/><EAN/><SWW/><NUMER_KATALOGOWY/><MPP>0</MPP></TOWAR><STAWKA_VAT><STAWKA>23.00</STAWKA><FLAGA>2</FLAGA><ZRODLOWA>0.00</ZRODLOWA></STAWKA_VAT><CENY><CENAZCZTEREMAMIEJSCAMI>0</CENAZCZTEREMAMIEJSCAMI><POCZATKOWA_WAL_CENNIKA>9.3000</POCZATKOWA_WAL_CENNIKA><POCZATKOWA_WAL_DOKUMENTU>9.3000</POCZATKOWA_WAL_DOKUMENTU><PO_RABACIE_WAL_CENNIKA>9.3000</PO_RABACIE_WAL_CENNIKA><PO_RABACIE_PLN>9.3000</PO_RABACIE_PLN><PO_RABACIE_WAL_DOKUMENTU>9.3000</PO_RABACIE_WAL_DOKUMENTU></CENY><WALUTA><SYMBOL>PLN</SYMBOL><KURS_L>1.00</KURS_L><KURS_M>1</KURS_M></WALUTA><RABAT>0.00</RABAT><WARTOSC_NETTO>22.68</WARTOSC_NETTO><WARTOSC_BRUTTO>27.90</WARTOSC_BRUTTO><WARTOSC_NETTO_WAL>22.68</WARTOSC_NETTO_WAL><WARTOSC_BRUTTO_WAL>27.90</WARTOSC_BRUTTO_WAL><ILOSC>3.0000</ILOSC><JM>szt</JM><JM_CALKOWITE>0.00</JM_CALKOWITE><JM_ZLOZONA><JMZ>szt</JMZ><JM_PRZELICZNIK_L>1.00</JM_PRZELICZNIK_L><JM_PRZELICZNIK_M>1</JM_PRZELICZNIK_M></JM_ZLOZONA></POZYCJA><POZYCJA><LP>18</LP><TOWAR><KOD>501389</KOD><NAZWA>DRUT NA  KOŁECZKU ŻARZONY - 100g (0,7mm x 70m)</NAZWA><OPIS/><EAN>501389</EAN><SWW/><NUMER_KATALOGOWY/><MPP>0</MPP></TOWAR><STAWKA_VAT><STAWKA>23.00</STAWKA><FLAGA>2</FLAGA><ZRODLOWA>0.00</ZRODLOWA></STAWKA_VAT><CENY><CENAZCZTEREMAMIEJSCAMI>0</CENAZCZTEREMAMIEJSCAMI><POCZATKOWA_WAL_CENNIKA>1.9000</POCZATKOWA_WAL_CENNIKA><POCZATKOWA_WAL_DOKUMENTU>1.9000</POCZATKOWA_WAL_DOKUMENTU><PO_RABACIE_WAL_CENNIKA>1.9000</PO_RABACIE_WAL_CENNIKA><PO_RABACIE_PLN>1.9000</PO_RABACIE_PLN><PO_RABACIE_WAL_DOKUMENTU>1.9000</PO_RABACIE_WAL_DOKUMENTU></CENY><WALUTA><SYMBOL>PLN</SYMBOL><KURS_L>1.00</KURS_L><KURS_M>1</KURS_M></WALUTA><RABAT>0.00</RABAT><WARTOSC_NETTO>1.54</WARTOSC_NETTO><WARTOSC_BRUTTO>1.90</WARTOSC_BRUTTO><WARTOSC_NETTO_WAL>1.54</WARTOSC_NETTO_WAL><WARTOSC_BRUTTO_WAL>1.90</WARTOSC_BRUTTO_WAL><ILOSC>1.0000</ILOSC><JM>szt.</JM><JM_CALKOWITE>0.00</JM_CALKOWITE><JM_ZLOZONA><JMZ>szt.</JMZ><JM_PRZELICZNIK_L>1.00</JM_PRZELICZNIK_L><JM_PRZELICZNIK_M>1</JM_PRZELICZNIK_M></JM_ZLOZONA></POZYCJA></POZYCJE><KAUCJE/><PLATNOSCI><PLATNOSC><FORMA>Karta</FORMA><TERMIN>2023-02-01</TERMIN><KWOTA>650.95</KWOTA><KWOTA_W_WAL_SYSTEMOWEJ>650.95</KWOTA_W_WAL_SYSTEMOWEJ><WALUTA><SYMBOL/><KURS_L>1.00</KURS_L><KURS_M>1</KURS_M></WALUTA></PLATNOSC></PLATNOSCI><PLATNOSCI_KAUCJE/><TABELKA_VAT><LINIA_VAT><STAWKA_VAT><STAWKA>23.00</STAWKA><FLAGA>2</FLAGA><ZRODLOWA>0.00</ZRODLOWA></STAWKA_VAT><NETTO>529.23</NETTO><VAT>121.72</VAT><BRUTTO>650.95</BRUTTO><NETTO_WAL>529.23</NETTO_WAL><VAT_WAL>121.72</VAT_WAL><BRUTTO_WAL>650.95</BRUTTO_WAL></LINIA_VAT></TABELKA_VAT><ATRYBUTY/></DOKUMENT></ROOT>
